sudoku_maker-1.0.12.dist-info/DESCRIPTION.rst
sudoku_maker-1.0.12.dist-info/RECORD
sudoku_maker-1.0.12.dist-info/metadata.json
sudoku_maker-1.0.12.dist-info/METADATA
sudoku_maker-1.0.12.dist-info/top_level.txt
sudoku_maker-1.0.12.dist-info/WHEEL
sudoku_maker-1.0.12.dist-info/entry_points.txt
sudoku_maker-1.0.12.data/data/my_data/data_file
sudoku_maker/sudoku_maker.py
sudoku_maker/__init__.py
