Metadata-Version: 2.0
Name: sudoku-maker
Version: 1.0.12
Summary: SudokuMaker which can make sudoku 4x4, 9x9, 16x16, …, 100x100.
Home-page: https://github.com/hooor/sudoku_maker_python
Author: yokkora
Author-email: none
License: MIT
Keywords: Games/Entertainment Puzzle Games
Platform: UNKNOWN
Classifier: Development Status :: 3 - Alpha
Classifier: Intended Audience :: Developers
Classifier: Topic :: Software Development :: Build Tools
Classifier: License :: OSI Approved :: MIT License
Classifier: Programming Language :: Python :: 2.6
Classifier: Programming Language :: Python :: 2.7
Classifier: Programming Language :: Python :: 3.2
Classifier: Programming Language :: Python :: 3.3
Classifier: Programming Language :: Python :: 3.4
Provides-Extra: dev
Requires-Dist: check-manifest; extra == 'dev'
Provides-Extra: test
Requires-Dist: coverage; extra == 'test'
